{
  "id": "t1-p33",
  "name": "Pogoda",
  "volume": "Tom I",
  "level": 1,
  "category": "Rzeczowniki",
  "chapter": "Rodział IV",
  "words": [
    {
      "id": "t1-p33-001",
      "english": "Rain",
      "polish": "Deszcz",
      "sentenceEn": "If it starts raining, we'll be in trouble.",
      "sentencePl": "Jeśli zacznie padać, będziemy mieli problem.",
      "audioWord": "t1-p33-001-word.mp3",
      "audioSentence": "t1-p33-001-sentence.mp3"
    },
    {
      "id": "t1-p33-002",
      "english": "Ice",
      "polish": "Lód",
      "sentenceEn": "There's ice on the road, be careful!",
      "sentencePl": "Na drodze jest lód, bądź ostrożny!",
      "audioWord": "t1-p33-002-word.mp3",
      "audioSentence": "t1-p33-002-sentence.mp3"
    },
    {
      "id": "t1-p33-003",
      "english": "Sky",
      "polish": "Niebo",
      "sentenceEn": "I love lying on the sand and looking up at the sky.",
      "sentencePl": "Uwielbiam leżeć na piasku i patrzeć w niebo.",
      "audioWord": "t1-p33-003-word.mp3",
      "audioSentence": "t1-p33-003-sentence.mp3"
    },
    {
      "id": "t1-p33-004",
      "english": "Weather",
      "polish": "Pogoda",
      "sentenceEn": "What's the weather like today? What should I wear?",
      "sentencePl": "Jaka jest dzisiaj pogoda? W co powinnam się ubrać?",
      "audioWord": "t1-p33-004-word.mp3",
      "audioSentence": "t1-p33-004-sentence.mp3"
    },
    {
      "id": "t1-p33-005",
      "english": "Air",
      "polish": "Powietrze",
      "sentenceEn": "We went to the shore to breathe in the sea air.",
      "sentencePl": "Poszliśmy na brzeg, aby powdychać morskie powietrze.",
      "audioWord": "t1-p33-005-word.mp3",
      "audioSentence": "t1-p33-005-sentence.mp3"
    },
    {
      "id": "t1-p33-006",
      "english": "Sun",
      "polish": "Słońce",
      "sentenceEn": "The sun comes up every day. It's no surprise.",
      "sentencePl": "Słońce wschodzi każdego dnia. Nie ma w tym nic zaskakującego.",
      "audioWord": "t1-p33-006-word.mp3",
      "audioSentence": "t1-p33-006-sentence.mp3"
    },
    {
      "id": "t1-p33-007",
      "english": "Degree celsius",
      "polish": "Stopień celsjusza",
      "sentenceEn": "The thermometer recorded a temperature of 40 Celsius degrees.",
      "sentencePl": "Termometr zarejestrował temperaturę 40 stopni Celsjusza.",
      "audioWord": "t1-p33-007-word.mp3",
      "audioSentence": "t1-p33-007-sentence.mp3"
    },
    {
      "id": "t1-p33-008",
      "english": "Snow",
      "polish": "Śnieg",
      "sentenceEn": "I can't wait for snow! I want to build a snowman.",
      "sentencePl": "Nie mogę się doczekać śniegu! Chcę ulepić bałwana.",
      "audioWord": "t1-p33-008-word.mp3",
      "audioSentence": "t1-p33-008-sentence.mp3"
    },
    {
      "id": "t1-p33-009",
      "english": "Temperature",
      "polish": "Temperatura",
      "sentenceEn": "I'm so tired of these temperatures. I miss winter.",
      "sentencePl": "Jestem zmęczony tymi temperaturami. Tęsknię za zimą.",
      "audioWord": "t1-p33-009-word.mp3",
      "audioSentence": "t1-p33-009-sentence.mp3"
    },
    {
      "id": "t1-p33-010",
      "english": "Wind",
      "polish": "Wiatr",
      "sentenceEn": "A wind from the west made the cruise difficult, and now our fish delivery is delayed.",
      "sentencePl": "Wiatr z zachodu utrudnił rejs i teraz nasza dostawa ryb jest opóźniona.",
      "audioWord": "t1-p33-010-word.mp3",
      "audioSentence": "t1-p33-010-sentence.mp3"
    },
    {
      "id": "t1-p33-011",
      "english": "Storm",
      "polish": "Burza",
      "sentenceEn": "A storm is coming. Let's get back home.",
      "sentencePl": "Nadchodzi burza. Wracajmy do domu.",
      "audioWord": "t1-p33-011-word.mp3",
      "audioSentence": "t1-p33-011-sentence.mp3"
    },
    {
      "id": "t1-p33-012",
      "english": "Cloud",
      "polish": "Chmura",
      "sentenceEn": "Many clouds are gathering. Are you sure it won't rain?",
      "sentencePl": "Zbiera się dużo chmur. Jesteś pewien, że nie będzie padać?",
      "audioWord": "t1-p33-012-word.mp3",
      "audioSentence": "t1-p33-012-sentence.mp3"
    },
    {
      "id": "t1-p33-013",
      "english": "Climate",
      "polish": "Klimat",
      "sentenceEn": "Climate changes terrify me.",
      "sentencePl": "Zmiany klimatu mnie przerażają.",
      "audioWord": "t1-p33-013-word.mp3",
      "audioSentence": "t1-p33-013-sentence.mp3"
    },
    {
      "id": "t1-p33-014",
      "english": "Fog",
      "polish": "Mgła",
      "sentenceEn": "Do you see this fog? I feel like I'm in a horror movie.",
      "sentencePl": "Widzisz tę mgłę? Czuję się jak w horrorze.",
      "audioWord": "t1-p33-014-word.mp3",
      "audioSentence": "t1-p33-014-sentence.mp3"
    },
    {
      "id": "t1-p33-015",
      "english": "Weather forecast",
      "polish": "Prognoza pogody",
      "sentenceEn": "You know that the weather forecast is usually wrong.",
      "sentencePl": "Wiesz, że prognozy pogodny zwykle się mylą.",
      "audioWord": "t1-p33-015-word.mp3",
      "audioSentence": "t1-p33-015-sentence.mp3"
    },
    {
      "id": "t1-p33-016",
      "english": "Degree",
      "polish": "Stopień",
      "sentenceEn": "Temperatures will reach 80 degrees tonight.",
      "sentencePl": "Temperatura sięgnie dzisiaj 80 stopni.",
      "audioWord": "t1-p33-016-word.mp3",
      "audioSentence": "t1-p33-016-sentence.mp3"
    },
    {
      "id": "t1-p33-017",
      "english": "Sunshine",
      "polish": "Blask słońca",
      "sentenceEn": "When I went outside after playing LoL all night, I was blinded by the sunshine.",
      "sentencePl": "Kiedy wyszedłem na dwór po całej nocy grania w LoLa, oślepił mnie blask słońca.",
      "audioWord": "t1-p33-017-word.mp3",
      "audioSentence": "t1-p33-017-sentence.mp3"
    },
    {
      "id": "t1-p33-018",
      "english": "Shade",
      "polish": "Cień (zacienione miejsce)",
      "sentenceEn": "Let's hang this hammock in the shade. It's gonna be great for naps.",
      "sentencePl": "Powieśmy ten hamak w cieniu. Będzie świetny na drzemki.",
      "audioWord": "t1-p33-018-word.mp3",
      "audioSentence": "t1-p33-018-sentence.mp3"
    },
    {
      "id": "t1-p33-019",
      "english": "Shadow",
      "polish": "Cień (czegoś)",
      "sentenceEn": "Toby tries to follow his shadow every time he is outside.",
      "sentencePl": "Toby próbuje śledzić swój cień za każdym razem, gdy jest na zewnątrz.",
      "audioWord": "t1-p33-019-word.mp3",
      "audioSentence": "t1-p33-019-sentence.mp3"
    },
    {
      "id": "t1-p33-020",
      "english": "Thunder",
      "polish": "Grzmot",
      "sentenceEn": "I am afraid of thunder because I have already been struck by lightning 4 times.",
      "sentencePl": "Boję się grzmotów, bo już 4 razy uderzył we mnie piorun.",
      "audioWord": "t1-p33-020-word.mp3",
      "audioSentence": "t1-p33-020-sentence.mp3"
    },
    {
      "id": "t1-p33-021",
      "english": "Frost",
      "polish": "Mróz",
      "sentenceEn": "The frost killed those flowers. I don't think I will win the gardening competition this year.",
      "sentencePl": "Mróz wykończył te kwiaty. Myślę, że w tym roku nie wygram konkursu ogrodniczego.",
      "audioWord": "t1-p33-021-word.mp3",
      "audioSentence": "t1-p33-021-sentence.mp3"
    },
    {
      "id": "t1-p33-022",
      "english": "Steam",
      "polish": "Para (wodna)",
      "sentenceEn": "I hate saunas! There is too much steam, and you can't see anything. That's why I sat on this guy ...",
      "sentencePl": "Nienawidzę sauny! Za dużo pary i nic nie widać. No i dlatego usiadłam na tym gościu...",
      "audioWord": "t1-p33-022-word.mp3",
      "audioSentence": "t1-p33-022-sentence.mp3"
    },
    {
      "id": "t1-p33-023",
      "english": "Rainbow",
      "polish": "Tęcza",
      "sentenceEn": "After the rain, you can find a rainbow in the sky.",
      "sentencePl": "Po deszczu na niebie można zobaczyć tęczę.",
      "audioWord": "t1-p33-023-word.mp3",
      "audioSentence": "t1-p33-023-sentence.mp3"
    },
    {
      "id": "t1-p33-024",
      "english": "Sunrise",
      "polish": "Wschód słońca",
      "sentenceEn": "Sunrise is the most beautiful part of the day, so I always wake up to see it.",
      "sentencePl": "Wschód słońca to najpiękniejsza pora dnia, więc zawsze budzę się tak, żeby go zobaczyć.",
      "audioWord": "t1-p33-024-word.mp3",
      "audioSentence": "t1-p33-024-sentence.mp3"
    },
    {
      "id": "t1-p33-025",
      "english": "Sunset",
      "polish": "Zachód słońca",
      "sentenceEn": "During sunset, he kissed me for the first time.",
      "sentencePl": "Podczas zachodu słońca pocałował mnie po raz pierwszy.",
      "audioWord": "t1-p33-025-word.mp3",
      "audioSentence": "t1-p33-025-sentence.mp3"
    },
    {
      "id": "t1-p33-026",
      "english": "Dry",
      "polish": "Suchy",
      "sentenceEn": "Sophia always drinks dry white wine with fish.",
      "sentencePl": "Zofia zawsze pije wytrawne białe wino do ryb.",
      "audioWord": "t1-p33-026-word.mp3",
      "audioSentence": "t1-p33-026-sentence.mp3"
    },
    {
      "id": "t1-p33-027",
      "english": "Rainy",
      "polish": "Deszczowy",
      "sentenceEn": "A rainy day. It's time to go to the bar.",
      "sentencePl": "Deszczowy dzień. Czas iść do baru.",
      "audioWord": "t1-p33-027-word.mp3",
      "audioSentence": "t1-p33-027-sentence.mp3"
    },
    {
      "id": "t1-p33-028",
      "english": "Icy",
      "polish": "Lodowaty",
      "sentenceEn": "I don't feel like swimming in this icy water.",
      "sentencePl": "Nie chce mi się pływać w tej lodowatej wodzie.",
      "audioWord": "t1-p33-028-word.mp3",
      "audioSentence": "t1-p33-028-sentence.mp3"
    },
    {
      "id": "t1-p33-029",
      "english": "Bright",
      "polish": "Jasny (np. Światło)",
      "sentenceEn": "Michael says bright colors suit me.",
      "sentencePl": "Michael mówi, że dobrze mi w jasnych kolorach.",
      "audioWord": "t1-p33-029-word.mp3",
      "audioSentence": "t1-p33-029-sentence.mp3"
    },
    {
      "id": "t1-p33-030",
      "english": "Cloudy",
      "polish": "Pochmurny",
      "sentenceEn": "The day is cloudy with a chance for storms. Better keep your Mercedes at home.",
      "sentencePl": "Dzień jest pochmurny i mogą wystąpić burze. Lepiej zostaw Mercedesa w domu.",
      "audioWord": "t1-p33-030-word.mp3",
      "audioSentence": "t1-p33-030-sentence.mp3"
    },
    {
      "id": "t1-p33-031",
      "english": "Sunny",
      "polish": "Słoneczny",
      "sentenceEn": "Another sunny morning in Miami. We're partying hard.",
      "sentencePl": "Kolejny słoneczny poranek w Miami. Imprezujemy na maksa.",
      "audioWord": "t1-p33-031-word.mp3",
      "audioSentence": "t1-p33-031-sentence.mp3"
    },
    {
      "id": "t1-p33-032",
      "english": "Snowy",
      "polish": "Śnieżny",
      "sentenceEn": "On one of these cold, snowy days, we decided to move to Miami.",
      "sentencePl": "Pewnego zimnego śnieżnego dnia postanowiliśmy przeprowadzić się do Miami.",
      "audioWord": "t1-p33-032-word.mp3",
      "audioSentence": "t1-p33-032-sentence.mp3"
    },
    {
      "id": "t1-p33-033",
      "english": "Windy",
      "polish": "Wietrzny",
      "sentenceEn": "The windy weather favors true sailors.",
      "sentencePl": "Wietrzna pogoda sprzyja prawdziwym żeglarzom.",
      "audioWord": "t1-p33-033-word.mp3",
      "audioSentence": "t1-p33-033-sentence.mp3"
    },
    {
      "id": "t1-p33-034",
      "english": "Frozen",
      "polish": "Mrożony; zamarznięty",
      "sentenceEn": "Han Solo was frozen in carbonite and transported to Jabba the Hutt.",
      "sentencePl": "Han Solo został zamrożony w karbonicie i przetransportowany do Jabby Hutta.",
      "audioWord": "t1-p33-034-word.mp3",
      "audioSentence": "t1-p33-034-sentence.mp3"
    },
    {
      "id": "t1-p33-035",
      "english": "Foggy",
      "polish": "Mglisty",
      "sentenceEn": "The foggy mornings in Innsmouth are still better than the nights. Demons and weird cults, a dangerous place.",
      "sentencePl": "Mgliste poranki w Innsmouth są i tak lepsze niż noce. Demony i dziwne kulty, niebezpieczne miejsce.",
      "audioWord": "t1-p33-035-word.mp3",
      "audioSentence": "t1-p33-035-sentence.mp3"
    },
    {
      "id": "t1-p33-036",
      "english": "Sandy",
      "polish": "Piaszczysty",
      "sentenceEn": "We should go to one of these sandy beaches. I want to lay down and chill.",
      "sentencePl": "Powinniśmy pójśc na jedną z tych piaszczystych plaż. Chcę się położyć i zrelaksować.",
      "audioWord": "t1-p33-036-word.mp3",
      "audioSentence": "t1-p33-036-sentence.mp3"
    },
    {
      "id": "t1-p33-037",
      "english": "Summer",
      "polish": "Letni (na porę roku)",
      "sentenceEn": "Of course, you can go to the seaside during your summer vacation.",
      "sentencePl": "Oczywiście podczas letnich wakacji możesz wybrać się nad morze.",
      "audioWord": "t1-p33-037-word.mp3",
      "audioSentence": "t1-p33-037-sentence.mp3"
    },
    {
      "id": "t1-p33-038",
      "english": "Autumn",
      "polish": "Jesienny",
      "sentenceEn": "I love this autumn weather. I can finally put on my favorite coat.",
      "sentencePl": "Kocham tę jesienną pogodę. Mogę w końcu nosić mój ulubiony płaszcz.",
      "audioWord": "t1-p33-038-word.mp3",
      "audioSentence": "t1-p33-038-sentence.mp3"
    },
    {
      "id": "t1-p33-039",
      "english": "Winter",
      "polish": "Zimowy (na porę roku)",
      "sentenceEn": "I don't remember the last time I saw snow in winter.",
      "sentencePl": "Nie pamiętam, kiedy ostatni raz widziałam śnieg zimą.",
      "audioWord": "t1-p33-039-word.mp3",
      "audioSentence": "t1-p33-039-sentence.mp3"
    },
    {
      "id": "t1-p33-040",
      "english": "Spring",
      "polish": "Wiosenny (w odniesieniu do pory roku)",
      "sentenceEn": "Spring is the most beautiful season. It's full of hope.",
      "sentencePl": "Wiosna to najpiękniejsza pora roku. Jest pełna nadziei.",
      "audioWord": "t1-p33-040-word.mp3",
      "audioSentence": "t1-p33-040-sentence.mp3"
    },
    {
      "id": "t1-p33-041",
      "english": "Thunderstorm",
      "polish": "Burza z piorunami",
      "sentenceEn": "The last thunderstorm left us without electricity.",
      "sentencePl": "Po ostatniej burzy byliśmy bez prądu.",
      "audioWord": "t1-p33-041-word.mp3",
      "audioSentence": "t1-p33-041-sentence.mp3"
    },
    {
      "id": "t1-p33-042",
      "english": "Darkness",
      "polish": "Ciemność",
      "sentenceEn": "Darkness covered the city. It got chilly and scary.",
      "sentencePl": "Ciemność przykryła miasto. Zrobiło się chłodno i strasznie.",
      "audioWord": "t1-p33-042-word.mp3",
      "audioSentence": "t1-p33-042-sentence.mp3"
    },
    {
      "id": "t1-p33-043",
      "english": "Hail",
      "polish": "Grad",
      "sentenceEn": "Everyone was hailing when we were passing through the city.",
      "sentencePl": "Wszyscy nas pozdrawiali, kiedy przejeżdżaliśmy przez miasto.",
      "audioWord": "t1-p33-043-word.mp3",
      "audioSentence": "t1-p33-043-sentence.mp3"
    },
    {
      "id": "t1-p33-044",
      "english": "Hurricane",
      "polish": "Huragan",
      "sentenceEn": "Hurricanes might appear in Florida during summer time.",
      "sentencePl": "W okresie letnim na Florydzie mogą pojawić się huragany.",
      "audioWord": "t1-p33-044-word.mp3",
      "audioSentence": "t1-p33-044-sentence.mp3"
    },
    {
      "id": "t1-p33-045",
      "english": "Drizzle",
      "polish": "Mżawka",
      "sentenceEn": "Oh, it is just a drizzle. I'm sure it will stop soon.",
      "sentencePl": "Oh, to tylko mżawka. Jestem pewna, że zaraz przestanie padać.",
      "audioWord": "t1-p33-045-word.mp3",
      "audioSentence": "t1-p33-045-sentence.mp3"
    },
    {
      "id": "t1-p33-046",
      "english": "Rainfall",
      "polish": "Opad deszczu",
      "sentenceEn": "Heavy rainfall ruined our vacation.",
      "sentencePl": "Ulewne opady deszczu zrujnowały nasze wakacje.",
      "audioWord": "t1-p33-046-word.mp3",
      "audioSentence": "t1-p33-046-sentence.mp3"
    },
    {
      "id": "t1-p33-047",
      "english": "Lightning",
      "polish": "Błyskawica",
      "sentenceEn": "As you can see I'm as fast as lightning.",
      "sentencePl": "Jak widzisz, jestem szybki niczym błyskawica.",
      "audioWord": "t1-p33-047-word.mp3",
      "audioSentence": "t1-p33-047-sentence.mp3"
    },
    {
      "id": "t1-p33-048",
      "english": "Flood",
      "polish": "Powódź",
      "sentenceEn": "The flood caused serious destruction to the town.",
      "sentencePl": "Powódź spowodowała poważne zniszczenia w mieście.",
      "audioWord": "t1-p33-048-word.mp3",
      "audioSentence": "t1-p33-048-sentence.mp3"
    },
    {
      "id": "t1-p33-049",
      "english": "Drought",
      "polish": "Susza",
      "sentenceEn": "The crops were scarce this year because of the drought.",
      "sentencePl": "Plony w tym roku były ubogie z powodu suszy.",
      "audioWord": "t1-p33-049-word.mp3",
      "audioSentence": "t1-p33-049-sentence.mp3"
    },
    {
      "id": "t1-p33-050",
      "english": "Snowfall",
      "polish": "Opad śniegu",
      "sentenceEn": "We never expected snowfall in Miami! I only have flip-flops.",
      "sentencePl": "Nigdy nie spodziewaliśmy się opadów śniegu w Miami! Mam tylko klapki.",
      "audioWord": "t1-p33-050-word.mp3",
      "audioSentence": "t1-p33-050-sentence.mp3"
    },
    {
      "id": "t1-p33-051",
      "english": "Moonlight",
      "polish": "Światło księżyca",
      "sentenceEn": "How softly your skin shines in the moonlight.",
      "sentencePl": "Jak cudownie błyszczy twoja skóra w świetle księżyca.",
      "audioWord": "t1-p33-051-word.mp3",
      "audioSentence": "t1-p33-051-sentence.mp3"
    },
    {
      "id": "t1-p33-052",
      "english": "Daylight",
      "polish": "Światło słoneczne",
      "sentenceEn": "Julie prefers to read in daylight. Artificial light spoils her eyes.",
      "sentencePl": "Julie woli czytać w świetle dziennym. Sztuczne światło psuje jej oczy.",
      "audioWord": "t1-p33-052-word.mp3",
      "audioSentence": "t1-p33-052-sentence.mp3"
    },
    {
      "id": "t1-p33-053",
      "english": "Downpour",
      "polish": "Ulewa",
      "sentenceEn": "We weren't prepared for the downpour. We came home barefoot because we were all wet anyway.",
      "sentencePl": "Nie byliśmy przygotowani na ulewę. Wróciliśmy do domu na bosaka, bo i tak byliśmy cali mokrzy.",
      "audioWord": "t1-p33-053-word.mp3",
      "audioSentence": "t1-p33-053-sentence.mp3"
    },
    {
      "id": "t1-p33-054",
      "english": "Heat",
      "polish": "Upał",
      "sentenceEn": "You can expect heat in Florida.",
      "sentencePl": "Na Florydzie należy się spodziewać upałów.",
      "audioWord": "t1-p33-054-word.mp3",
      "audioSentence": "t1-p33-054-sentence.mp3"
    },
    {
      "id": "t1-p33-055",
      "english": "Nightfall",
      "polish": "Nadejście nocy (zmrok)",
      "sentenceEn": "We have to hurry. I don't want to get back at nightfall.",
      "sentencePl": "Musimy się spieszyć. Nie chcę wracać o zmroku.",
      "audioWord": "t1-p33-055-word.mp3",
      "audioSentence": "t1-p33-055-sentence.mp3"
    }
  ]
}