{
  "id": "t1-p407",
  "name": "Człowiek jest piękny",
  "volume": "Tom IV",
  "level": 3,
  "category": "Slang",
  "chapter": "Rozdział XL",
  "words": [
    {
      "id": "t1-p407-001",
      "english": "Alluring",
      "polish": "Kusząca",
      "sentenceEn": null,
      "sentencePl": null,
      "audioWord": "t1-p407-001-word.mp3",
      "audioWordPl": "t1-p407-001-word-pl.mp3",
      "audioSentence": "t1-p407-001-sentence.mp3"
    },
    {
      "id": "t1-p407-002",
      "english": "Angelic",
      "polish": "Anielska",
      "sentenceEn": null,
      "sentencePl": null,
      "audioWord": "t1-p407-002-word.mp3",
      "audioWordPl": "t1-p407-002-word-pl.mp3",
      "audioSentence": "t1-p407-002-sentence.mp3"
    },
    {
      "id": "t1-p407-003",
      "english": "Banging",
      "polish": "Superancka",
      "sentenceEn": null,
      "sentencePl": null,
      "audioWord": "t1-p407-003-word.mp3",
      "audioWordPl": "t1-p407-003-word-pl.mp3",
      "audioSentence": "t1-p407-003-sentence.mp3"
    },
    {
      "id": "t1-p407-004",
      "english": "Eye-catching",
      "polish": "Przykuwa wzrok",
      "sentenceEn": null,
      "sentencePl": null,
      "audioWord": "t1-p407-004-word.mp3",
      "audioWordPl": "t1-p407-004-word-pl.mp3",
      "audioSentence": "t1-p407-004-sentence.mp3"
    },
    {
      "id": "t1-p407-005",
      "english": "Foxy",
      "polish": "Laseczka",
      "sentenceEn": null,
      "sentencePl": null,
      "audioWord": "t1-p407-005-word.mp3",
      "audioWordPl": "t1-p407-005-word-pl.mp3",
      "audioSentence": "t1-p407-005-sentence.mp3"
    },
    {
      "id": "t1-p407-006",
      "english": "Graceful",
      "polish": "Pełna gracji",
      "sentenceEn": null,
      "sentencePl": null,
      "audioWord": "t1-p407-006-word.mp3",
      "audioWordPl": "t1-p407-006-word-pl.mp3",
      "audioSentence": "t1-p407-006-sentence.mp3"
    },
    {
      "id": "t1-p407-007",
      "english": "Mesmerizing",
      "polish": "Hipnotyzująca",
      "sentenceEn": null,
      "sentencePl": null,
      "audioWord": "t1-p407-007-word.mp3",
      "audioWordPl": "t1-p407-007-word-pl.mp3",
      "audioSentence": "t1-p407-007-sentence.mp3"
    },
    {
      "id": "t1-p407-008",
      "english": "Phenomenal",
      "polish": "Zjawiskowa",
      "sentenceEn": null,
      "sentencePl": null,
      "audioWord": "t1-p407-008-word.mp3",
      "audioWordPl": "t1-p407-008-word-pl.mp3",
      "audioSentence": "t1-p407-008-sentence.mp3"
    },
    {
      "id": "t1-p407-009",
      "english": "Sensuous",
      "polish": "Zmysłowa",
      "sentenceEn": null,
      "sentencePl": null,
      "audioWord": "t1-p407-009-word.mp3",
      "audioWordPl": "t1-p407-009-word-pl.mp3",
      "audioSentence": "t1-p407-009-sentence.mp3"
    },
    {
      "id": "t1-p407-010",
      "english": "Striking beauty",
      "polish": "Uderzające piękno",
      "sentenceEn": null,
      "sentencePl": null,
      "audioWord": "t1-p407-010-word.mp3",
      "audioWordPl": "t1-p407-010-word-pl.mp3",
      "audioSentence": "t1-p407-010-sentence.mp3"
    }
  ]
}