{
  "id": "t1-p258",
  "name": "Kraje",
  "volume": "Tom III",
  "level": 2,
  "category": "Rzeczowniki",
  "chapter": "Rozdział XXVI",
  "words": [
    {
      "id": "t1-p258-001",
      "english": "Serbian",
      "polish": "Serbka",
      "sentenceEn": null,
      "sentencePl": null,
      "audioWord": "t1-p258-001-word.mp3",
      "audioSentence": "t1-p258-001-sentence.mp3"
    },
    {
      "id": "t1-p258-002",
      "english": "Slovakia",
      "polish": "Słowacja",
      "sentenceEn": null,
      "sentencePl": null,
      "audioWord": "t1-p258-002-word.mp3",
      "audioSentence": "t1-p258-002-sentence.mp3"
    },
    {
      "id": "t1-p258-003",
      "english": "Slovak",
      "polish": "Słowaczka",
      "sentenceEn": null,
      "sentencePl": null,
      "audioWord": "t1-p258-003-word.mp3",
      "audioSentence": "t1-p258-003-sentence.mp3"
    },
    {
      "id": "t1-p258-004",
      "english": "Scotland",
      "polish": "Szkocja",
      "sentenceEn": null,
      "sentencePl": null,
      "audioWord": "t1-p258-004-word.mp3",
      "audioSentence": "t1-p258-004-sentence.mp3"
    },
    {
      "id": "t1-p258-005",
      "english": "Scottish",
      "polish": "Szkotka",
      "sentenceEn": null,
      "sentencePl": null,
      "audioWord": "t1-p258-005-word.mp3",
      "audioSentence": "t1-p258-005-sentence.mp3"
    },
    {
      "id": "t1-p258-006",
      "english": "Sweden",
      "polish": "Szwecja",
      "sentenceEn": null,
      "sentencePl": null,
      "audioWord": "t1-p258-006-word.mp3",
      "audioSentence": "t1-p258-006-sentence.mp3"
    },
    {
      "id": "t1-p258-007",
      "english": "Swedish",
      "polish": "Szwedka",
      "sentenceEn": null,
      "sentencePl": null,
      "audioWord": "t1-p258-007-word.mp3",
      "audioSentence": "t1-p258-007-sentence.mp3"
    },
    {
      "id": "t1-p258-008",
      "english": "Ukraine",
      "polish": "Ukraina",
      "sentenceEn": null,
      "sentencePl": null,
      "audioWord": "t1-p258-008-word.mp3",
      "audioSentence": "t1-p258-008-sentence.mp3"
    },
    {
      "id": "t1-p258-009",
      "english": "Ukrainian",
      "polish": "Ukrainka",
      "sentenceEn": null,
      "sentencePl": null,
      "audioWord": "t1-p258-009-word.mp3",
      "audioSentence": "t1-p258-009-sentence.mp3"
    },
    {
      "id": "t1-p258-010",
      "english": "Mexico",
      "polish": "Meksyk",
      "sentenceEn": null,
      "sentencePl": null,
      "audioWord": "t1-p258-010-word.mp3",
      "audioSentence": "t1-p258-010-sentence.mp3"
    },
    {
      "id": "t1-p258-011",
      "english": "Mexican",
      "polish": "Meksykanka",
      "sentenceEn": null,
      "sentencePl": null,
      "audioWord": "t1-p258-011-word.mp3",
      "audioSentence": "t1-p258-011-sentence.mp3"
    },
    {
      "id": "t1-p258-012",
      "english": "Switzerland",
      "polish": "Szwajcaria",
      "sentenceEn": null,
      "sentencePl": null,
      "audioWord": "t1-p258-012-word.mp3",
      "audioSentence": "t1-p258-012-sentence.mp3"
    },
    {
      "id": "t1-p258-013",
      "english": "Swiss",
      "polish": "Szwajcarka",
      "sentenceEn": null,
      "sentencePl": null,
      "audioWord": "t1-p258-013-word.mp3",
      "audioSentence": "t1-p258-013-sentence.mp3"
    },
    {
      "id": "t1-p258-014",
      "english": "Romania",
      "polish": "Rumunia",
      "sentenceEn": null,
      "sentencePl": null,
      "audioWord": "t1-p258-014-word.mp3",
      "audioSentence": "t1-p258-014-sentence.mp3"
    },
    {
      "id": "t1-p258-015",
      "english": "Romanian",
      "polish": "Rumunka",
      "sentenceEn": null,
      "sentencePl": null,
      "audioWord": "t1-p258-015-word.mp3",
      "audioSentence": "t1-p258-015-sentence.mp3"
    }
  ]
}