{
  "id": "t1-p753",
  "name": "Fantasy",
  "volume": "Tom VIII",
  "level": 4,
  "category": "Rzeczowniki",
  "chapter": "Rozdział LXXV",
  "words": [
    {
      "id": "t1-p753-001",
      "english": "Magic wand",
      "polish": "Magiczna różdżka",
      "sentenceEn": null,
      "sentencePl": null,
      "audioWord": "t1-p753-001-word.mp3",
      "audioSentence": "t1-p753-001-sentence.mp3"
    },
    {
      "id": "t1-p753-002",
      "english": "Magician",
      "polish": "Magik",
      "sentenceEn": null,
      "sentencePl": null,
      "audioWord": "t1-p753-002-word.mp3",
      "audioSentence": "t1-p753-002-sentence.mp3"
    },
    {
      "id": "t1-p753-003",
      "english": "Manuscript",
      "polish": "Manuskrypt",
      "sentenceEn": null,
      "sentencePl": null,
      "audioWord": "t1-p753-003-word.mp3",
      "audioSentence": "t1-p753-003-sentence.mp3"
    },
    {
      "id": "t1-p753-004",
      "english": "Medusa",
      "polish": "Meduza",
      "sentenceEn": null,
      "sentencePl": null,
      "audioWord": "t1-p753-004-word.mp3",
      "audioSentence": "t1-p753-004-sentence.mp3"
    },
    {
      "id": "t1-p753-005",
      "english": "Sword",
      "polish": "Miecz",
      "sentenceEn": null,
      "sentencePl": null,
      "audioWord": "t1-p753-005-word.mp3",
      "audioSentence": "t1-p753-005-sentence.mp3"
    },
    {
      "id": "t1-p753-006",
      "english": "Minotaur",
      "polish": "Minotaur",
      "sentenceEn": null,
      "sentencePl": null,
      "audioWord": "t1-p753-006-word.mp3",
      "audioSentence": "t1-p753-006-sentence.mp3"
    },
    {
      "id": "t1-p753-007",
      "english": "Mystic",
      "polish": "Mistyk",
      "sentenceEn": null,
      "sentencePl": null,
      "audioWord": "t1-p753-007-word.mp3",
      "audioSentence": "t1-p753-007-sentence.mp3"
    },
    {
      "id": "t1-p753-008",
      "english": "Mummy",
      "polish": "Mumia",
      "sentenceEn": null,
      "sentencePl": null,
      "audioWord": "t1-p753-008-word.mp3",
      "audioSentence": "t1-p753-008-sentence.mp3"
    },
    {
      "id": "t1-p753-009",
      "english": "Undead",
      "polish": "Nieumarły",
      "sentenceEn": null,
      "sentencePl": null,
      "audioWord": "t1-p753-009-word.mp3",
      "audioSentence": "t1-p753-009-sentence.mp3"
    },
    {
      "id": "t1-p753-010",
      "english": "Occultism",
      "polish": "Okultyzm",
      "sentenceEn": null,
      "sentencePl": null,
      "audioWord": "t1-p753-010-word.mp3",
      "audioSentence": "t1-p753-010-sentence.mp3"
    },
    {
      "id": "t1-p753-011",
      "english": "Orc",
      "polish": "Ork",
      "sentenceEn": null,
      "sentencePl": null,
      "audioWord": "t1-p753-011-word.mp3",
      "audioSentence": "t1-p753-011-sentence.mp3"
    },
    {
      "id": "t1-p753-012",
      "english": "Pegasus",
      "polish": "Pegaz",
      "sentenceEn": null,
      "sentencePl": null,
      "audioWord": "t1-p753-012-word.mp3",
      "audioSentence": "t1-p753-012-sentence.mp3"
    },
    {
      "id": "t1-p753-013",
      "english": "Pentagram",
      "polish": "Pentagram",
      "sentenceEn": null,
      "sentencePl": null,
      "audioWord": "t1-p753-013-word.mp3",
      "audioSentence": "t1-p753-013-sentence.mp3"
    },
    {
      "id": "t1-p753-014",
      "english": "Portal",
      "polish": "Portal",
      "sentenceEn": null,
      "sentencePl": null,
      "audioWord": "t1-p753-014-word.mp3",
      "audioSentence": "t1-p753-014-sentence.mp3"
    },
    {
      "id": "t1-p753-015",
      "english": "Curse",
      "polish": "Przekleństwo",
      "sentenceEn": null,
      "sentencePl": null,
      "audioWord": "t1-p753-015-word.mp3",
      "audioSentence": "t1-p753-015-sentence.mp3"
    }
  ]
}