{
  "id": "t1-p22",
  "name": "Rodzina",
  "volume": "Tom I",
  "level": 1,
  "category": "Rzeczowniki",
  "chapter": "Rozdział III",
  "words": [
    {
      "id": "t1-p22-001",
      "english": "Brother",
      "polish": "Brat",
      "sentenceEn": "It's good to have a brother. He will always have your back.",
      "sentencePl": "Dobrze jest mieć brata. Zawsze będzie Cię wspierał.",
      "audioWord": "t1-p22-001-word.mp3",
      "audioSentence": "t1-p22-001-sentence.mp3"
    },
    {
      "id": "t1-p22-002",
      "english": "Daughter",
      "polish": "Córka",
      "sentenceEn": "Sophia's daughter looks exactly like her. Like two peas in a pod.",
      "sentencePl": "Córka Sofii wygląda dokładnie jak ona. Są podobne jak dwie krople wody.",
      "audioWord": "t1-p22-002-word.mp3",
      "audioSentence": "t1-p22-002-sentence.mp3"
    },
    {
      "id": "t1-p22-003",
      "english": "Children",
      "polish": "Dzieci",
      "sentenceEn": "How many children would you like to have? I think 3 is enough.",
      "sentencePl": "Ile chciałbyś mieć dzieci? Myślę, że 3 wystarczy.",
      "audioWord": "t1-p22-003-word.mp3",
      "audioSentence": "t1-p22-003-sentence.mp3"
    },
    {
      "id": "t1-p22-004",
      "english": "Child",
      "polish": "Dziecko",
      "sentenceEn": "James is not my child, but my brother's.",
      "sentencePl": "James nie jest moim dzieckiem, to syn mojego brata.",
      "audioWord": "t1-p22-004-word.mp3",
      "audioSentence": "t1-p22-004-sentence.mp3"
    },
    {
      "id": "t1-p22-005",
      "english": "Mother",
      "polish": "Matka",
      "sentenceEn": "No one will love you like your mother.",
      "sentencePl": "Nikt nie będzie Cię kochał tak jak matka.",
      "audioWord": "t1-p22-005-word.mp3",
      "audioSentence": "t1-p22-005-sentence.mp3"
    },
    {
      "id": "t1-p22-006",
      "english": "Husband",
      "polish": "Mąż",
      "sentenceEn": "My husband is very supportive. I'm lucky.",
      "sentencePl": "Mój mąż bardzo mnie wspiera. Szczęściara ze mnie.",
      "audioWord": "t1-p22-006-word.mp3",
      "audioSentence": "t1-p22-006-sentence.mp3"
    },
    {
      "id": "t1-p22-007",
      "english": "Father",
      "polish": "Ojciec",
      "sentenceEn": "My father always believed in me. That is why I know I can face anything.",
      "sentencePl": "Mój ojciec zawsze we mnie wierzył. I właśnie dlatego wiem, że stawię czoło wszystkiemu.",
      "audioWord": "t1-p22-007-word.mp3",
      "audioSentence": "t1-p22-007-sentence.mp3"
    },
    {
      "id": "t1-p22-008",
      "english": "Family",
      "polish": "Rodzina",
      "sentenceEn": "I love to spend time with my whole family once a year... and that's enough.",
      "sentencePl": "Kocham raz do roku spędzać czas z całą moją rodziną... i tyle wystarczy.",
      "audioWord": "t1-p22-008-word.mp3",
      "audioSentence": "t1-p22-008-sentence.mp3"
    },
    {
      "id": "t1-p22-009",
      "english": "Son",
      "polish": "Syn",
      "sentenceEn": "My son loves doing sports. He spends all of his free time on the field.",
      "sentencePl": "Mój syn kocha uprawiać sporty. Cały wolny czas spędza na boisku.",
      "audioWord": "t1-p22-009-word.mp3",
      "audioSentence": "t1-p22-009-sentence.mp3"
    },
    {
      "id": "t1-p22-010",
      "english": "Wife",
      "polish": "Żona",
      "sentenceEn": "I have the best wife in the world... Did she hear?",
      "sentencePl": "Mam najlepszą żonę na świecie... Słyszała?",
      "audioWord": "t1-p22-010-word.mp3",
      "audioSentence": "t1-p22-010-sentence.mp3"
    },
    {
      "id": "t1-p22-011",
      "english": "Grandma",
      "polish": "Babcia",
      "sentenceEn": "Psst, grandma always has candies in her purse.",
      "sentencePl": "Psst, babcia ma zawsze w torebce cukierki.",
      "audioWord": "t1-p22-011-word.mp3",
      "audioSentence": "t1-p22-011-sentence.mp3"
    },
    {
      "id": "t1-p22-012",
      "english": "Grandmother",
      "polish": "Babka (matka matki)",
      "sentenceEn": "My grandmother bakes the best cookies! You must try them!",
      "sentencePl": "Moja babcia piecze najlepsze ciasteczka! Musisz ich spróbować.",
      "audioWord": "t1-p22-012-word.mp3",
      "audioSentence": "t1-p22-012-sentence.mp3"
    },
    {
      "id": "t1-p22-013",
      "english": "Aunt",
      "polish": "Ciotka",
      "sentenceEn": "Your aunt is so nice! My dad wants to know if she's single.",
      "sentencePl": "Twoja ciocia jest taka fajna! Mój tata chciałby wiedzieć, czy jest wolna.",
      "audioWord": "t1-p22-013-word.mp3",
      "audioSentence": "t1-p22-013-sentence.mp3"
    },
    {
      "id": "t1-p22-014",
      "english": "Grandfather",
      "polish": "Dziadek",
      "sentenceEn": "I think our grandfather is the oldest man in town. He will be 99 this summer.",
      "sentencePl": "Wydaje mi się, że nasz dziadek jest najstarszym mężczyzną w mieście. Tego lata skończy 99 lat.",
      "audioWord": "t1-p22-014-word.mp3",
      "audioSentence": "t1-p22-014-sentence.mp3"
    },
    {
      "id": "t1-p22-015",
      "english": "Grandpa",
      "polish": "Dziadzio",
      "sentenceEn": "My grandpa keeps losing his glasses. He has like 3 extra pairs.",
      "sentencePl": "Mój dziadzio ciągle gubi swoje okulary. Ma ze trzy zapasowe pary.",
      "audioWord": "t1-p22-015-word.mp3",
      "audioSentence": "t1-p22-015-sentence.mp3"
    },
    {
      "id": "t1-p22-016",
      "english": "Cousin",
      "polish": "Kuzyn; kuzynka",
      "sentenceEn": "I love spending time with my cousins. We do all kinds of crazy stuff together.",
      "sentencePl": "Uwielbiam spędzać czas z moimi kuzynami. Robimy razem różne szalone rzeczy.",
      "audioWord": "t1-p22-016-word.mp3",
      "audioSentence": "t1-p22-016-sentence.mp3"
    },
    {
      "id": "t1-p22-017",
      "english": "Baby",
      "polish": "Niemowlę",
      "sentenceEn": "Lili is just a baby. She can't dance yet.",
      "sentencePl": "Lili jest niemowlakiem. Nie umie jeszcze tańczyć.",
      "audioWord": "t1-p22-017-word.mp3",
      "audioSentence": "t1-p22-017-sentence.mp3"
    },
    {
      "id": "t1-p22-018",
      "english": "Parent",
      "polish": "Rodzic",
      "sentenceEn": "It's not easy to be parents of teenegers. They don't want to talk to us.",
      "sentencePl": "Nie jest łatwo być rodzicami nastolatków. Nie chcą z nami rozmawiać.",
      "audioWord": "t1-p22-018-word.mp3",
      "audioSentence": "t1-p22-018-sentence.mp3"
    },
    {
      "id": "t1-p22-019",
      "english": "Sister",
      "polish": "Siostra",
      "sentenceEn": "My sister is also my best friend. We tell each other everything.",
      "sentencePl": "Moja siostra jest też moją najlepszą przyjaciółką. Mówimy sobie wszystko.",
      "audioWord": "t1-p22-019-word.mp3",
      "audioSentence": "t1-p22-019-sentence.mp3"
    },
    {
      "id": "t1-p22-020",
      "english": "Uncle",
      "polish": "Wujek",
      "sentenceEn": "My uncle makes his own craft beer. You can try it at the Beach Bar.",
      "sentencePl": "Mój wujek warzy własne piwo kraftowe. Możesz go spróbować w Beach Barze.",
      "audioWord": "t1-p22-020-word.mp3",
      "audioSentence": "t1-p22-020-sentence.mp3"
    },
    {
      "id": "t1-p22-021",
      "english": "Twin",
      "polish": "Bliźniak",
      "sentenceEn": "Why do people name their twins so similarly and later dress them in identical clothes?",
      "sentencePl": "Po co ludzie dają podobne imiona bliźniakom, a potem ubierają je w identyczne ubrania?",
      "audioWord": "t1-p22-021-word.mp3",
      "audioSentence": "t1-p22-021-sentence.mp3"
    },
    {
      "id": "t1-p22-022",
      "english": "Only child",
      "polish": "Jedynak; jedynaczka",
      "sentenceEn": "Being an only child was great. You have your parents all to yourself. They are crazy about you, but well...",
      "sentencePl": "Bycie jedynakiem było świetne. Masz wtedy rodziców tylko dla siebie. Mają fioła na Twoim punkcie, ale cóż...",
      "audioWord": "t1-p22-022-word.mp3",
      "audioSentence": "t1-p22-022-sentence.mp3"
    },
    {
      "id": "t1-p22-023",
      "english": "Relative",
      "polish": "Krewny",
      "sentenceEn": "You know it's all relative, right? Your perspective always depends on your position.",
      "sentencePl": "Wiesz, że to wszystko jest względne, prawda? Twoja perspektywa zawsze zależy od Twojej pozycji.",
      "audioWord": "t1-p22-023-word.mp3",
      "audioSentence": "t1-p22-023-sentence.mp3"
    },
    {
      "id": "t1-p22-024",
      "english": "Mom",
      "polish": "Mama",
      "sentenceEn": "My mom always helps me with my problems.",
      "sentencePl": "Moja mama zawsze pomaga mi rozwiązać moje problemy.",
      "audioWord": "t1-p22-024-word.mp3",
      "audioSentence": "t1-p22-024-sentence.mp3"
    },
    {
      "id": "t1-p22-025",
      "english": "Siblings",
      "polish": "Rodzeństwo",
      "sentenceEn": "- Would you rather have siblings, or be an only child? - Always siblings!",
      "sentencePl": "- Wolałbyś mieć rodzeństwo, czy być jedynakiem? - Zawsze wybrałbym rodzeństwo!",
      "audioWord": "t1-p22-025-word.mp3",
      "audioSentence": "t1-p22-025-sentence.mp3"
    },
    {
      "id": "t1-p22-026",
      "english": "Niece",
      "polish": "Siostrzenica; bratanica",
      "sentenceEn": "Sir David's niece studies at Crimson School.",
      "sentencePl": "Siostrzenica Sir Davida uczy się w Crimson School.",
      "audioWord": "t1-p22-026-word.mp3",
      "audioSentence": "t1-p22-026-sentence.mp3"
    },
    {
      "id": "t1-p22-027",
      "english": "Nephew",
      "polish": "Siostrzeniec; bratanek",
      "sentenceEn": "I don't want to have children. My nephew is enough.",
      "sentencePl": "Nie chcę mieć dzieci. Wystarcza mi mój bratanek.",
      "audioWord": "t1-p22-027-word.mp3",
      "audioSentence": "t1-p22-027-sentence.mp3"
    },
    {
      "id": "t1-p22-028",
      "english": "Dad",
      "polish": "Tata",
      "sentenceEn": "I will ask dad. He won't say no to his little girl.",
      "sentencePl": "Poproszę tatę. On nie odmówi swojej małej córeczce.",
      "audioWord": "t1-p22-028-word.mp3",
      "audioSentence": "t1-p22-028-sentence.mp3"
    },
    {
      "id": "t1-p22-029",
      "english": "Mother-in-law",
      "polish": "Teściowa",
      "sentenceEn": "Do you have good relations with your mother-in-law?",
      "sentencePl": "Masz dobre relacje ze swoją teściową?",
      "audioWord": "t1-p22-029-word.mp3",
      "audioSentence": "t1-p22-029-sentence.mp3"
    },
    {
      "id": "t1-p22-030",
      "english": "Father-in-law",
      "polish": "Teść",
      "sentenceEn": "How is your father-in-law? Is he feeling better?",
      "sentencePl": "Co u Twojego teścia? Czuje się lepiej?",
      "audioWord": "t1-p22-030-word.mp3",
      "audioSentence": "t1-p22-030-sentence.mp3"
    },
    {
      "id": "t1-p22-031",
      "english": "Grandchildren",
      "polish": "Wnuki",
      "sentenceEn": "If we don't do anything, even our grandchildren will be learning through ITizen.",
      "sentencePl": "Jeśli nic nie zrobimy, to nawet nasze wnuki będą się uczyć przez ITizena.",
      "audioWord": "t1-p22-031-word.mp3",
      "audioSentence": "t1-p22-031-sentence.mp3"
    },
    {
      "id": "t1-p22-032",
      "english": "Family life",
      "polish": "Życie rodzinne",
      "sentenceEn": "You can combine work and family life. You just have to be very well organized.",
      "sentencePl": "Da się łączyć pracę z życiem rodzinnym. Po prostu trzeba być bardzo dobrze zorganizowanym.",
      "audioWord": "t1-p22-032-word.mp3",
      "audioSentence": "t1-p22-032-sentence.mp3"
    },
    {
      "id": "t1-p22-033",
      "english": "Daughter-in-law",
      "polish": "Synowa",
      "sentenceEn": "We're spending Christmas at our son's. Our daughter-in-law will prepare something tasty to eat. She's an amazing cook.",
      "sentencePl": "Spędzamy Święta Bożego Narodzenia u syna. Nasza synowa upichci coś smacznego. Jest niesamowitą kucharką.",
      "audioWord": "t1-p22-033-word.mp3",
      "audioSentence": "t1-p22-033-sentence.mp3"
    },
    {
      "id": "t1-p22-034",
      "english": "Grandson",
      "polish": "Wnuk",
      "sentenceEn": "Our grandson is visiting us this month.",
      "sentencePl": "W tym miesiącu odwiedza nas nasz wnuk.",
      "audioWord": "t1-p22-034-word.mp3",
      "audioSentence": "t1-p22-034-sentence.mp3"
    },
    {
      "id": "t1-p22-035",
      "english": "Son-in-law",
      "polish": "Zięć",
      "sentenceEn": "My son-in-law had asked for my permission before he proposed to my daughter.",
      "sentencePl": "Mój zięć poprosił mnie o zgodę, zanim oświadczył się mojej córce.",
      "audioWord": "t1-p22-035-word.mp3",
      "audioSentence": "t1-p22-035-sentence.mp3"
    },
    {
      "id": "t1-p22-036",
      "english": "Kinship",
      "polish": "Powinowactwo; pokrewieństwo",
      "sentenceEn": "What kind of kinship is between you and George?",
      "sentencePl": "Jakie pokrewieństwo łączy Cię z Georgem?",
      "audioWord": "t1-p22-036-word.mp3",
      "audioSentence": "t1-p22-036-sentence.mp3"
    },
    {
      "id": "t1-p22-037",
      "english": "Great-grandmother",
      "polish": "Prababcia",
      "sentenceEn": "My great-grandmother left me a notebook with all of her recipes.",
      "sentencePl": "Moja prababcia zostawiła mi notes ze swoimi przepisami.",
      "audioWord": "t1-p22-037-word.mp3",
      "audioSentence": "t1-p22-037-sentence.mp3"
    },
    {
      "id": "t1-p22-038",
      "english": "Great-grandfather",
      "polish": "Pradziadek",
      "sentenceEn": "We still live in a house my great-grandfather built.",
      "sentencePl": "Ciągle mieszkamy w domu, który zbudował mój pradziadek.",
      "audioWord": "t1-p22-038-word.mp3",
      "audioSentence": "t1-p22-038-sentence.mp3"
    },
    {
      "id": "t1-p22-039",
      "english": "Brother-in-law",
      "polish": "Szwagier",
      "sentenceEn": "My brother-in-law and I like each other a lot, and we often meet to watch the games together.",
      "sentencePl": "Bardzo się ze szwagrem lubimy i często spotykamy się, aby oglądać razem mecze.",
      "audioWord": "t1-p22-039-word.mp3",
      "audioSentence": "t1-p22-039-sentence.mp3"
    },
    {
      "id": "t1-p22-040",
      "english": "Sister-in-law",
      "polish": "Szwagierka",
      "sentenceEn": "That's my sister-in-law, not my wife. But we do seem to be really close.",
      "sentencePl": "To moja szwagierka, nie żona. Ale chyba faktycznie widać, że jesteśmy ze sobą zżyci.",
      "audioWord": "t1-p22-040-word.mp3",
      "audioSentence": "t1-p22-040-sentence.mp3"
    },
    {
      "id": "t1-p22-041",
      "english": "Heritage",
      "polish": "Dziedzictwo",
      "sentenceEn": "Cultural heritage is not only made up of literature and art.",
      "sentencePl": "Dziedzictwo kulturowe to nie tylko literatura i sztuka.",
      "audioWord": "t1-p22-041-word.mp3",
      "audioSentence": "t1-p22-041-sentence.mp3"
    },
    {
      "id": "t1-p22-042",
      "english": "Legacy",
      "polish": "Spuścizna",
      "sentenceEn": "Roger gambled away all his father's legacy playing in the casino.",
      "sentencePl": "Roger przegrał całą spuściznę swojego ojca, grając w kasynie.",
      "audioWord": "t1-p22-042-word.mp3",
      "audioSentence": "t1-p22-042-sentence.mp3"
    },
    {
      "id": "t1-p22-043",
      "english": "Godson",
      "polish": "Chrześniak",
      "sentenceEn": "This is James, my godson. He'll be joining us today for the training.",
      "sentencePl": "To jest James, mój chrześniak. Będzie dzisiaj z nami trenował.",
      "audioWord": "t1-p22-043-word.mp3",
      "audioSentence": "t1-p22-043-sentence.mp3"
    },
    {
      "id": "t1-p22-044",
      "english": "Goddaughter",
      "polish": "Chrześnica",
      "sentenceEn": "My goddaughter turns 18. It's time to buy her a Bentley.",
      "sentencePl": "Moja chrześnica kończy 18 lat. Czas kupić jej Bentleya.",
      "audioWord": "t1-p22-044-word.mp3",
      "audioSentence": "t1-p22-044-sentence.mp3"
    },
    {
      "id": "t1-p22-045",
      "english": "Godmother",
      "polish": "Matka chrzestna",
      "sentenceEn": "She did ask me to be a godmother to one of her children.",
      "sentencePl": "Poprosiła mnie, żebym została matką chrzestną jednego z jej dzieci.",
      "audioWord": "t1-p22-045-word.mp3",
      "audioSentence": "t1-p22-045-sentence.mp3"
    },
    {
      "id": "t1-p22-046",
      "english": "Godfather",
      "polish": "Ojciec chrzestny",
      "sentenceEn": "Will Prince Harry be the godfather?",
      "sentencePl": "Czy ojcem chrzestnym będzie książę Harry?",
      "audioWord": "t1-p22-046-word.mp3",
      "audioSentence": "t1-p22-046-sentence.mp3"
    },
    {
      "id": "t1-p22-047",
      "english": "Great-great-grandmother",
      "polish": "Praprababcia",
      "sentenceEn": "My great-great-grandmother was French. We still use her amazing recipes.",
      "sentencePl": "Moja praprababcia była Francuzką. Wciąż korzystamy z jej niesamowitych przepisów.",
      "audioWord": "t1-p22-047-word.mp3",
      "audioSentence": "t1-p22-047-sentence.mp3"
    },
    {
      "id": "t1-p22-048",
      "english": "Great-great-grandfather",
      "polish": "Prapradziadek",
      "sentenceEn": "Kate's great-great-grandfather left her a huge inheritance, and now she can live comfortably.",
      "sentencePl": "Prapradziadek Kate zostawił jej wielki spadek i teraz może żyć wygodnie.",
      "audioWord": "t1-p22-048-word.mp3",
      "audioSentence": "t1-p22-048-sentence.mp3"
    },
    {
      "id": "t1-p22-049",
      "english": "Half-sister",
      "polish": "Siostra przyrodnia",
      "sentenceEn": "The only one who can get through to him is his half-sister, Sunna.",
      "sentencePl": "Jedyną osobą, która może do niego dotrzeć, jest jego przyrodnia siostra, Sunna.",
      "audioWord": "t1-p22-049-word.mp3",
      "audioSentence": "t1-p22-049-sentence.mp3"
    },
    {
      "id": "t1-p22-050",
      "english": "Half-brother",
      "polish": "Brat przyrodni",
      "sentenceEn": "Tom is one of my four half-brothers. My dad had a little too much fun after the divorce.",
      "sentencePl": "Tom to jeden z moich czterech przyrodnich braci. Mój tata trochę za bardzo się bawił po rozwodzie.",
      "audioWord": "t1-p22-050-word.mp3",
      "audioSentence": "t1-p22-050-sentence.mp3"
    }
  ]
}