{
  "id": "t1-p689",
  "name": "Pogoda",
  "volume": "Tom VII",
  "level": 4,
  "category": "Rzeczowniki",
  "chapter": "Rozdział LXVIII",
  "words": [
    {
      "id": "t1-p689-001",
      "english": "Cloudiness",
      "polish": "Zachmurzenie",
      "sentenceEn": null,
      "sentencePl": null,
      "audioWord": "t1-p689-001-word.mp3",
      "audioWordPl": "t1-p689-001-word-pl.mp3",
      "audioSentence": "t1-p689-001-sentence.mp3"
    },
    {
      "id": "t1-p689-002",
      "english": "Snow drift",
      "polish": "Zaspa",
      "sentenceEn": null,
      "sentencePl": null,
      "audioWord": "t1-p689-002-word.mp3",
      "audioWordPl": "t1-p689-002-word-pl.mp3",
      "audioSentence": "t1-p689-002-sentence.mp3"
    },
    {
      "id": "t1-p689-003",
      "english": "Sunray",
      "polish": "Promień słoneczny",
      "sentenceEn": null,
      "sentencePl": null,
      "audioWord": "t1-p689-003-word.mp3",
      "audioWordPl": "t1-p689-003-word-pl.mp3",
      "audioSentence": "t1-p689-003-sentence.mp3"
    },
    {
      "id": "t1-p689-004",
      "english": "Dew",
      "polish": "Rosa",
      "sentenceEn": null,
      "sentencePl": null,
      "audioWord": "t1-p689-004-word.mp3",
      "audioWordPl": "t1-p689-004-word-pl.mp3",
      "audioSentence": "t1-p689-004-sentence.mp3"
    },
    {
      "id": "t1-p689-005",
      "english": "Blizzard",
      "polish": "Zamieć śnieżna",
      "sentenceEn": null,
      "sentencePl": null,
      "audioWord": "t1-p689-005-word.mp3",
      "audioWordPl": "t1-p689-005-word-pl.mp3",
      "audioSentence": "t1-p689-005-sentence.mp3"
    },
    {
      "id": "t1-p689-006",
      "english": "Foul weather",
      "polish": "Słota",
      "sentenceEn": null,
      "sentencePl": null,
      "audioWord": "t1-p689-006-word.mp3",
      "audioWordPl": "t1-p689-006-word-pl.mp3",
      "audioSentence": "t1-p689-006-sentence.mp3"
    },
    {
      "id": "t1-p689-007",
      "english": "Slob",
      "polish": "Plucha",
      "sentenceEn": null,
      "sentencePl": null,
      "audioWord": "t1-p689-007-word.mp3",
      "audioWordPl": "t1-p689-007-word-pl.mp3",
      "audioSentence": "t1-p689-007-sentence.mp3"
    },
    {
      "id": "t1-p689-008",
      "english": "Sleet",
      "polish": "Śnieg z deszczem",
      "sentenceEn": null,
      "sentencePl": null,
      "audioWord": "t1-p689-008-word.mp3",
      "audioWordPl": "t1-p689-008-word-pl.mp3",
      "audioSentence": "t1-p689-008-sentence.mp3"
    },
    {
      "id": "t1-p689-009",
      "english": "Whirlwind",
      "polish": "Trąba powietrzna",
      "sentenceEn": null,
      "sentencePl": null,
      "audioWord": "t1-p689-009-word.mp3",
      "audioWordPl": "t1-p689-009-word-pl.mp3",
      "audioSentence": "t1-p689-009-sentence.mp3"
    },
    {
      "id": "t1-p689-010",
      "english": "Snowflake",
      "polish": "Płatek śniegu",
      "sentenceEn": null,
      "sentencePl": null,
      "audioWord": "t1-p689-010-word.mp3",
      "audioWordPl": "t1-p689-010-word-pl.mp3",
      "audioSentence": "t1-p689-010-sentence.mp3"
    },
    {
      "id": "t1-p689-011",
      "english": "Gust",
      "polish": "Podmuch",
      "sentenceEn": null,
      "sentencePl": null,
      "audioWord": "t1-p689-011-word.mp3",
      "audioWordPl": "t1-p689-011-word-pl.mp3",
      "audioSentence": "t1-p689-011-sentence.mp3"
    },
    {
      "id": "t1-p689-012",
      "english": "Gale",
      "polish": "Wichura",
      "sentenceEn": null,
      "sentencePl": null,
      "audioWord": "t1-p689-012-word.mp3",
      "audioWordPl": "t1-p689-012-word-pl.mp3",
      "audioSentence": "t1-p689-012-sentence.mp3"
    },
    {
      "id": "t1-p689-013",
      "english": "Blizzard",
      "polish": "Zamieć śnieżna",
      "sentenceEn": null,
      "sentencePl": null,
      "audioWord": "t1-p689-013-word.mp3",
      "audioWordPl": "t1-p689-013-word-pl.mp3",
      "audioSentence": "t1-p689-013-sentence.mp3"
    },
    {
      "id": "t1-p689-014",
      "english": "Thaw",
      "polish": "Odwilż",
      "sentenceEn": null,
      "sentencePl": null,
      "audioWord": "t1-p689-014-word.mp3",
      "audioWordPl": "t1-p689-014-word-pl.mp3",
      "audioSentence": "t1-p689-014-sentence.mp3"
    },
    {
      "id": "t1-p689-015",
      "english": "Black ice",
      "polish": "Gołoledź",
      "sentenceEn": null,
      "sentencePl": null,
      "audioWord": "t1-p689-015-word.mp3",
      "audioWordPl": "t1-p689-015-word-pl.mp3",
      "audioSentence": "t1-p689-015-sentence.mp3"
    }
  ]
}