{
  "id": "t1-p343",
  "name": "Ruch abstrakcyjny",
  "volume": "Tom IV",
  "level": 3,
  "category": "Phrasale",
  "chapter": "Rozdział XXXIV",
  "words": [
    {
      "id": "t1-p343-001",
      "english": "Be in",
      "polish": "Wchodzić w coś",
      "sentenceEn": null,
      "sentencePl": null,
      "audioWord": "t1-p343-001-word.mp3",
      "audioSentence": "t1-p343-001-sentence.mp3"
    },
    {
      "id": "t1-p343-002",
      "english": "Give up",
      "polish": "Przestać coś robić",
      "sentenceEn": null,
      "sentencePl": null,
      "audioWord": "t1-p343-002-word.mp3",
      "audioSentence": "t1-p343-002-sentence.mp3"
    },
    {
      "id": "t1-p343-003",
      "english": "Be left over",
      "polish": "Pozostać",
      "sentenceEn": null,
      "sentencePl": null,
      "audioWord": "t1-p343-003-word.mp3",
      "audioSentence": "t1-p343-003-sentence.mp3"
    },
    {
      "id": "t1-p343-004",
      "english": "Get in",
      "polish": "Dostać się",
      "sentenceEn": null,
      "sentencePl": null,
      "audioWord": "t1-p343-004-word.mp3",
      "audioSentence": "t1-p343-004-sentence.mp3"
    },
    {
      "id": "t1-p343-005",
      "english": "Get over",
      "polish": "Dochodzić do siebie",
      "sentenceEn": null,
      "sentencePl": null,
      "audioWord": "t1-p343-005-word.mp3",
      "audioSentence": "t1-p343-005-sentence.mp3"
    },
    {
      "id": "t1-p343-006",
      "english": "Give way",
      "polish": "Ustępować",
      "sentenceEn": null,
      "sentencePl": null,
      "audioWord": "t1-p343-006-word.mp3",
      "audioSentence": "t1-p343-006-sentence.mp3"
    },
    {
      "id": "t1-p343-007",
      "english": "Get into sth",
      "polish": "Dostać się do środka czegoś",
      "sentenceEn": null,
      "sentencePl": null,
      "audioWord": "t1-p343-007-word.mp3",
      "audioSentence": "t1-p343-007-sentence.mp3"
    },
    {
      "id": "t1-p343-008",
      "english": "Get into",
      "polish": "Zaangażować się",
      "sentenceEn": null,
      "sentencePl": null,
      "audioWord": "t1-p343-008-word.mp3",
      "audioSentence": "t1-p343-008-sentence.mp3"
    },
    {
      "id": "t1-p343-009",
      "english": "Get into sth",
      "polish": "Wplątać się",
      "sentenceEn": null,
      "sentencePl": null,
      "audioWord": "t1-p343-009-word.mp3",
      "audioSentence": "t1-p343-009-sentence.mp3"
    },
    {
      "id": "t1-p343-010",
      "english": "Stick with",
      "polish": "Trzymać się",
      "sentenceEn": null,
      "sentencePl": null,
      "audioWord": "t1-p343-010-word.mp3",
      "audioSentence": "t1-p343-010-sentence.mp3"
    }
  ]
}