{
  "id": "t1-p228",
  "name": "Czasowniki 30",
  "volume": "Tom IX",
  "level": 4,
  "category": "Czasowniki",
  "chapter": "Rozdział LXXXVI",
  "words": [
    {
      "id": "t1-p228-001",
      "english": "Visualize",
      "polish": "Wizualizować",
      "sentenceEn": "We'll describe the application in detail, so you can visualize it better.",
      "sentencePl": "Opiszemy aplikację ze szczegółami, byście mogli ją lepiej sobie wyobrazić.",
      "audioWord": "t1-p228-001-word.mp3",
      "audioSentence": "t1-p228-001-sentence.mp3"
    },
    {
      "id": "t1-p228-002",
      "english": "Allocate",
      "polish": "Alokować",
      "sentenceEn": "The company allocated half of its budget to research.",
      "sentencePl": "Firma alokowała połowę swojego budżetu na badania.",
      "audioWord": "t1-p228-002-word.mp3",
      "audioSentence": "t1-p228-002-sentence.mp3"
    },
    {
      "id": "t1-p228-003",
      "english": "Aspire",
      "polish": "Aspirować",
      "sentenceEn": "You aspire to a job in an international company or abroad.",
      "sentencePl": "Aspirujesz do pracy w międzynarodowej firmie lub za granicą.",
      "audioWord": "t1-p228-003-word.mp3",
      "audioSentence": "t1-p228-003-sentence.mp3"
    },
    {
      "id": "t1-p228-004",
      "english": "Assimilate",
      "polish": "Asymilować (się)",
      "sentenceEn": "Some people never assimilate, but most do.",
      "sentencePl": "Niektórzy ludzie nigdy się nie asymilują, ale większość tak.",
      "audioWord": "t1-p228-004-word.mp3",
      "audioSentence": "t1-p228-004-sentence.mp3"
    },
    {
      "id": "t1-p228-005",
      "english": "Capitalize",
      "polish": "Kapitalizować; skorzystać (najczęściej finansowo) na czymś",
      "sentenceEn": "We capitalized on our last business idea and made thousands!",
      "sentencePl": "Skapitalizowaliśmy nasz ostatni pomysł na biznes i zarobiliśmy tysiące!",
      "audioWord": "t1-p228-005-word.mp3",
      "audioSentence": "t1-p228-005-sentence.mp3"
    },
    {
      "id": "t1-p228-006",
      "english": "Compile",
      "polish": "Kompilować (przetwarzać); ujmować w zbiór",
      "sentenceEn": "Compiling the code takes some time.",
      "sentencePl": "Kompilowanie kodu zajmuje trochę czasu.",
      "audioWord": "t1-p228-006-word.mp3",
      "audioSentence": "t1-p228-006-sentence.mp3"
    },
    {
      "id": "t1-p228-007",
      "english": "Confront",
      "polish": "Konfrontować (coś z czymś, z kimś)",
      "sentenceEn": "Bobby, you cannot hide under the bed your whole life. You must confront problems. Besides, your wife is worried.",
      "sentencePl": "Bobby, nie możesz chować się pod łóżkiem przez całe życie. Musisz się konfrontować z problemami. Poza tym Twoja żona się martwi.",
      "audioWord": "t1-p228-007-word.mp3",
      "audioSentence": "t1-p228-007-sentence.mp3"
    },
    {
      "id": "t1-p228-008",
      "english": "Constitute",
      "polish": "Konstytuować; stanowić",
      "sentenceEn": "The closing of the embassy constitutes a violation of international law.",
      "sentencePl": "Zamknięcie ambasady stanowi naruszenie prawa międzynarodowego.",
      "audioWord": "t1-p228-008-word.mp3",
      "audioSentence": "t1-p228-008-sentence.mp3"
    },
    {
      "id": "t1-p228-009",
      "english": "Contemplate",
      "polish": "Kontemplować",
      "sentenceEn": "No more contemplating. Let's get to work!",
      "sentencePl": "Koniec kontemplowania. Weźmy się do pracy!",
      "audioWord": "t1-p228-009-word.mp3",
      "audioSentence": "t1-p228-009-sentence.mp3"
    },
    {
      "id": "t1-p228-010",
      "english": "Culminate",
      "polish": "Kulminować; ukoronować",
      "sentenceEn": "Their summer tour will culminate at a spectacular concert in Miami.",
      "sentencePl": "Ich letnią trasę ukoronuje spektakularny koncert w Miami.",
      "audioWord": "t1-p228-010-word.mp3",
      "audioSentence": "t1-p228-010-sentence.mp3"
    },
    {
      "id": "t1-p228-011",
      "english": "Degrade",
      "polish": "Degradować; poniżać",
      "sentenceEn": "She's too proud to degrade herself like that!",
      "sentencePl": "Jest zbuy dumna, żeby się tak poniżyć!",
      "audioWord": "t1-p228-011-word.mp3",
      "audioSentence": "t1-p228-011-sentence.mp3"
    },
    {
      "id": "t1-p228-012",
      "english": "Diversify",
      "polish": "Dywersyfikować",
      "sentenceEn": "It's high time to diversify our government a bit and take down the High Council.",
      "sentencePl": "Najwyższa pora zdywersyfikować trochę nasz rząd i obalić Najwyższą Radę.",
      "audioWord": "t1-p228-012-word.mp3",
      "audioSentence": "t1-p228-012-sentence.mp3"
    },
    {
      "id": "t1-p228-013",
      "english": "Dramatize",
      "polish": "Dramatyzować",
      "sentenceEn": "I think it is important not to dramatize the situation. Let's all calm down.",
      "sentencePl": "Najważniejsze to nie dramatyzować. Uspokójmy się wszyscy.",
      "audioWord": "t1-p228-013-word.mp3",
      "audioSentence": "t1-p228-013-sentence.mp3"
    },
    {
      "id": "t1-p228-014",
      "english": "Dub",
      "polish": "Dubingować",
      "sentenceEn": "Sheila dubbed the latest animated movie for kids.",
      "sentencePl": "Sheila dubbingowała najnowszy film animowany dla dzieci.",
      "audioWord": "t1-p228-014-word.mp3",
      "audioSentence": "t1-p228-014-sentence.mp3"
    },
    {
      "id": "t1-p228-015",
      "english": "Emanate",
      "polish": "Emanować",
      "sentenceEn": "I felt the warmth emanating from her heart. She was that special someone.",
      "sentencePl": "Poczułem ciepło emanujące z jej serca. Była kimś wyjątkowym.",
      "audioWord": "t1-p228-015-word.mp3",
      "audioSentence": "t1-p228-015-sentence.mp3"
    }
  ]
}